luna/radiology/__init__.py
luna/radiology/cli/__init__.py
luna/radiology/cli/coregister_volumes.py
luna/radiology/cli/dicom_to_itk.py
luna/radiology/cli/extract_radiomics.py
luna/radiology/cli/extract_voxels.py
luna/radiology/cli/generate_scan_table.py
luna/radiology/cli/match_metadata.py
luna/radiology/cli/randomize_contours.py
luna/radiology/cli/window_volume.py
luna/radiology/common/__init__.py
luna/radiology/common/preprocess.py
luna/radiology/mirp/__init__.py
luna/radiology/mirp/imageClass.py
luna/radiology/mirp/imagePerturbations.py
luna/radiology/mirp/imageProcess.py
luna/radiology/mirp/imageReaders.py
luna/radiology/mirp/importSettings.py
luna/radiology/mirp/roiClass.py
luna/radiology/mirp/utilities.py
luna/radiology/proxy_table/__init__.py
luna/radiology/proxy_table/data_ingestion_template_schema.yml
luna/radiology/proxy_table/generate.py
luna/radiology/proxy_table/annotation/__init__.py
luna/radiology/proxy_table/annotation/generate.py
luna/radiology/refined_table/__init__.py
luna/radiology/refined_table/cli.py
luna/radiology/refined_table/dicom_to_scan.py
luna/radiology/refined_table/generate.py
luna/radiology/refined_table/annotation/__init__.py
luna/radiology/refined_table/annotation/generate.py
luna/radiology/unpack_images/__init__.py
luna/radiology/unpack_images/unpack.py
tests/__init__.py
tests/test_config.yml
tests/luna/__init__.py
tests/luna/radiology/__init__.py
tests/luna/radiology/cli/__init__.py
tests/luna/radiology/cli/test_dicom_to_itk.py
tests/luna/radiology/cli/test_extract_radiomics.py
tests/luna/radiology/cli/test_extract_voxels.py
tests/luna/radiology/cli/test_generate_scan_table.py
tests/luna/radiology/cli/test_window_volume.py
tests/luna/radiology/cli/testdata/123/SCANS/3/DICOM/1-01.dcm
tests/luna/radiology/cli/testdata/123/SCANS/3/DICOM/1-02.dcm
tests/luna/radiology/cli/testdata/123/SCANS/3/DICOM/1-03.dcm
tests/luna/radiology/cli/testdata/123/SCANS/3/DICOM/1-04.dcm
tests/luna/radiology/cli/testdata/123/SCANS/3/DICOM/1-05.dcm
pyluna_radiology-0.3.3.dist-info/METADATA
pyluna_radiology-0.3.3.dist-info/WHEEL
pyluna_radiology-0.3.3.dist-info/entry_points.txt
pyluna_radiology-0.3.3.dist-info/top_level.txt
pyluna_radiology-0.3.3.dist-info/zip-safe
pyluna_radiology-0.3.3.dist-info/RECORD
